{"name":"testdb73832","description":"testdb73832","packageName":"com.test873923.testdb73832","draft":false,"tables":[{"name":"TABLE1","oldName":"TABLE1","entityName":"Table1","type":"TABLE","schema":"PUBLIC","catalog":"PUBLIC","columns":[{"name":"ID","oldName":"ID","fieldName":"id","sqlType":"integer","hibernateType":"integer","length":255,"precision":19,"nullable":false,"defaultValue":"","generator":"identity","generatorValue":null,"partOfAnyRelation":true,"primaryKey":true,"unique":true,"foreignKey":false,"partOfPrimaryKey":true},{"name":"COLUMN2","oldName":"COLUMN2","fieldName":"column2","sqlType":"integer","hibernateType":"integer","length":255,"precision":19,"nullable":true,"defaultValue":"0","generator":"assigned","generatorValue":null,"partOfAnyRelation":false,"primaryKey":false,"unique":false,"foreignKey":false,"partOfPrimaryKey":false},{"name":"COLUMN3","oldName":"COLUMN3","fieldName":"column3","sqlType":"string","hibernateType":"string","length":255,"precision":19,"nullable":true,"defaultValue":null,"generator":"assigned","generatorValue":null,"partOfAnyRelation":false,"primaryKey":false,"unique":false,"foreignKey":false,"partOfPrimaryKey":false}],"primaryKey":{"name":"SYS_PK_10092","virtual":false,"columns":["ID"],"composite":false},"relations":[{"name":"FK_NBU25VYW53CXC139LLOACIYBL","fieldName":"table4s","cardinality":"OneToMany","sourceTable":"TABLE1","targetTable":"TABLE4","mappings":[{"sourceColumn":"ID","targetColumn":"COLUMN3"}],"primary":false,"virtual":false,"composite":false,"selfRelation":false}],"constraints":[],"fullyQualifiedName":"com.test873923.testdb73832.Table1","oldColumnNames":{"ID":"ID","COLUMN2":"COLUMN2","COLUMN3":"COLUMN3"}},{"name":"TABLE4","oldName":"TABLE4","entityName":"Table4","type":"TABLE","schema":"PUBLIC","catalog":"PUBLIC","columns":[{"name":"COLUMN2","oldName":"COLUMN2","fieldName":"column2","sqlType":"integer","hibernateType":"integer","length":255,"precision":19,"nullable":false,"defaultValue":"0","generator":"assigned","generatorValue":null,"partOfAnyRelation":false,"primaryKey":false,"unique":false,"foreignKey":false,"partOfPrimaryKey":false},{"name":"ID","oldName":"ID","fieldName":"id","sqlType":"integer","hibernateType":"integer","length":255,"precision":19,"nullable":false,"defaultValue":"","generator":"assigned","generatorValue":null,"partOfAnyRelation":false,"primaryKey":false,"unique":false,"foreignKey":false,"partOfPrimaryKey":true},{"name":"COLUMN3","oldName":"COLUMN3","fieldName":"table1","sqlType":"integer","hibernateType":"integer","length":255,"precision":19,"nullable":false,"defaultValue":"0","generator":"assigned","generatorValue":null,"partOfAnyRelation":true,"primaryKey":false,"unique":false,"foreignKey":true,"partOfPrimaryKey":false}],"primaryKey":{"name":"SYS_PK_10097","virtual":false,"columns":["COLUMN2","ID"],"composite":true},"relations":[{"name":"FK_NBU25VYW53CXC139LLOACIYBL","fieldName":"table1","cardinality":"ManyToOne","sourceTable":"TABLE4","targetTable":"TABLE1","mappings":[{"sourceColumn":"COLUMN3","targetColumn":"ID"}],"primary":true,"virtual":false,"composite":false,"selfRelation":false}],"constraints":[],"fullyQualifiedName":"com.test873923.testdb73832.Table4","oldColumnNames":{"COLUMN2":"COLUMN2","ID":"ID","COLUMN3":"COLUMN3"}}]}